Metadata-Version: 1.0
Name: two-prob-distributions
Version: 0.1
Summary: Gaussian and Binomial distributions
Home-page: UNKNOWN
Author: Eswar
Author-email: eswarjgs@gmail.com
License: UNKNOWN
Platform: UNKNOWN
